svc_from_callable/__init__.py
svc_from_callable/app/__init__.py
svc_from_callable/app/handler.py
svc_from_callable/app/main.py
svc_from_callable/app/middleware.py
svc_from_callable/app/routes.py
svc_from_callable/app/types.py
svc_from_callable-0.1.8.dist-info/METADATA
svc_from_callable-0.1.8.dist-info/WHEEL
svc_from_callable-0.1.8.dist-info/RECORD
