Metadata-Version: 2.3
Name: svc-from-callable
Version: 0.1.8
Summary: 
Author: Your Name
Author-email: you@example.com
Requires-Python: >=3.10,<4.0
Classifier: Programming Language :: Python :: 3
Classifier: Programming Language :: Python :: 3.10
Classifier: Programming Language :: Python :: 3.11
Classifier: Programming Language :: Python :: 3.12
Classifier: Programming Language :: Python :: 3.13
Requires-Dist: sw-product-lib (>=0.9.12,<0.10.0)
Requires-Dist: uvicorn (>=0.23.2,<0.24.0)
